MANIFEST.in
README.txt
qt.conf
setup.py
PyQt5/Enginio.dll
PyQt5/Enginio.pyd
PyQt5/QAxContainer.pyd
PyQt5/Qt.pyd
PyQt5/Qt5Bluetooth.dll
PyQt5/Qt5CLucene.dll
PyQt5/Qt5Concurrent.dll
PyQt5/Qt5Core.dll
PyQt5/Qt5Declarative.dll
PyQt5/Qt5Designer.dll
PyQt5/Qt5DesignerComponents.dll
PyQt5/Qt5Gui.dll
PyQt5/Qt5Help.dll
PyQt5/Qt5Multimedia.dll
PyQt5/Qt5MultimediaQuick_p.dll
PyQt5/Qt5MultimediaWidgets.dll
PyQt5/Qt5Network.dll
PyQt5/Qt5Nfc.dll
PyQt5/Qt5OpenGL.dll
PyQt5/Qt5Positioning.dll
PyQt5/Qt5PrintSupport.dll
PyQt5/Qt5Qml.dll
PyQt5/Qt5Quick.dll
PyQt5/Qt5QuickParticles.dll
PyQt5/Qt5QuickTest.dll
PyQt5/Qt5QuickWidgets.dll
PyQt5/Qt5Script.dll
PyQt5/Qt5ScriptTools.dll
PyQt5/Qt5Sensors.dll
PyQt5/Qt5SerialPort.dll
PyQt5/Qt5Sql.dll
PyQt5/Qt5Svg.dll
PyQt5/Qt5Test.dll
PyQt5/Qt5WebKit.dll
PyQt5/Qt5WebKitWidgets.dll
PyQt5/Qt5WebSockets.dll
PyQt5/Qt5Widgets.dll
PyQt5/Qt5WinExtras.dll
PyQt5/Qt5Xml.dll
PyQt5/Qt5XmlPatterns.dll
PyQt5/QtBluetooth.pyd
PyQt5/QtCore.pyd
PyQt5/QtDesigner.pyd
PyQt5/QtGui.pyd
PyQt5/QtHelp.pyd
PyQt5/QtMultimedia.pyd
PyQt5/QtMultimediaWidgets.pyd
PyQt5/QtNetwork.pyd
PyQt5/QtOpenGL.pyd
PyQt5/QtPositioning.pyd
PyQt5/QtPrintSupport.pyd
PyQt5/QtQml.pyd
PyQt5/QtQuick.pyd
PyQt5/QtQuickWidgets.pyd
PyQt5/QtSensors.pyd
PyQt5/QtSerialPort.pyd
PyQt5/QtSql.pyd
PyQt5/QtSvg.pyd
PyQt5/QtTest.pyd
PyQt5/QtWebKit.pyd
PyQt5/QtWebKitWidgets.pyd
PyQt5/QtWebProcess.exe
PyQt5/QtWebSockets.pyd
PyQt5/QtWidgets.pyd
PyQt5/QtWinExtras.pyd
PyQt5/QtXmlPatterns.pyd
PyQt5/_QOpenGLFunctions_ES2.pyd
PyQt5/__init__.py
PyQt5/assistant.exe
PyQt5/d3dcompiler_47.dll
PyQt5/designer.exe
PyQt5/dumpcpp.exe
PyQt5/dumpdoc.exe
PyQt5/icudt52.dll
PyQt5/icuin52.dll
PyQt5/icuuc52.dll
PyQt5/idc.exe
PyQt5/lconvert.exe
PyQt5/libEGL.dll
PyQt5/libGLESv2.dll
PyQt5/libeay32.dll
PyQt5/libmysql.dll
PyQt5/linguist.exe
PyQt5/lrelease.exe
PyQt5/lupdate.exe
PyQt5/moc.exe
PyQt5/pixeltool.exe
PyQt5/qcollectiongenerator.exe
PyQt5/qdoc.exe
PyQt5/qhelpconverter.exe
PyQt5/qhelpgenerator.exe
PyQt5/qlalr.exe
PyQt5/qmake.exe
python_qt5.egg-info/PKG-INFO
python_qt5.egg-info/SOURCES.txt
python_qt5.egg-info/dependency_links.txt
python_qt5.egg-info/not-zip-safe
python_qt5.egg-info/top_level.txt