Metadata-Version: 1.1
Name: python-qt5
Version: 0.1.8
Summary: PyQt5
Home-page: https://github.com/pyqt/python-qt5
Author: Marcus Ottosson
Author-email: marcus@abstractfactory.com
License: GPLv3
Platform: UNKNOWN
Classifier: Development Status :: 4 - Beta
Classifier: Intended Audience :: Developers
Classifier: License :: OSI Approved :: GNU General Public License v3 (GPLv3)
Classifier: Programming Language :: Python
Classifier: Programming Language :: Python :: 2
Classifier: Programming Language :: Python :: 2.7
Classifier: Topic :: Software Development :: Libraries :: Python Modules
Classifier: Topic :: Utilities
